gramedia/__init__.py
gramedia/common/__init__.py
gramedia/common/cli.py
gramedia/common/env.py
gramedia/common/http.py
gramedia/common/jsonschema.py
gramedia/django/__init__.py
gramedia/django/abstract_models.py
gramedia/django/amqp_connection.py
gramedia/django/drf.py
gramedia/django/jsonschema.py
gramedia/django/models.py
gramedia/django/serializers.py
gramedia/django/signalling.py
gramedia/django/queue/__init__.py
gramedia/django/queue/security/__init__.py
gramedia/django/queue/security/access_group_user.py
gramedia/django/utils/__init__.py
gramedia/django/utils/db.py
gramedia/django/utils/helpers.py
gramedia/django/utils/models.py
gramedia/django/utils/permissions.py
gramedia/django/utils/test_helper.py
gdn_python_common-0.9.2.dist-info/METADATA
gdn_python_common-0.9.2.dist-info/WHEEL
gdn_python_common-0.9.2.dist-info/top_level.txt
gdn_python_common-0.9.2.dist-info/RECORD
