Metadata-Version: 2.1
Name: gdn-python-common
Version: 0.9.2
Summary: Various non-framework specific web helpers.
Home-page: https://engineering.gramedia.digital
Author: Gramedia Digital Nusantara Team
Author-email: engineering@gramedia.digital
License: GPLv3+
Project-URL: Documentation, https://gdn-python-common.rtfd.io/
Project-URL: Source, https://github.com/gramedia-digital-nusantara/python-common
Project-URL: Tracker, https://github.com/gramedia-digital-nusantara/python-common/issues
Classifier: Development Status :: 4 - Beta
Classifier: Intended Audience :: Developers
Classifier: Natural Language :: English
Classifier: License :: OSI Approved :: GNU General Public License v3 or later (GPLv3+)
Classifier: Operating System :: OS Independent
Classifier: Programming Language :: Python :: 3.6
Classifier: Topic :: Software Development :: Libraries :: Python Modules
Requires-Dist: humanize (>=0.5.1)
Requires-Dist: jsonschema (>=2.6.0)
Provides-Extra: drf
Requires-Dist: djangorestframework (>=3.6.2) ; extra == 'drf'
Requires-Dist: django (>=1.11.15) ; extra == 'drf'
Requires-Dist: djangorestframework-camel-case (>=1.1.2) ; extra == 'drf'
Requires-Dist: django-autoslug (>=1.9.8) ; extra == 'drf'
